kimi_craw/__init__.py
kimi_craw/main.py
kimi_craw/configs/__init__.py
kimi_craw/configs/header_config.py
kimi_craw/core/__init__.py
kimi_craw/core/chat.py
kimi_craw/core/token.py
kimi_craw/utils/__init__.py
kimi_craw/utils/utils.py
kimi_craw-1.0.5.dist-info/LICENSE
kimi_craw-1.0.5.dist-info/METADATA
kimi_craw-1.0.5.dist-info/WHEEL
kimi_craw-1.0.5.dist-info/top_level.txt
kimi_craw-1.0.5.dist-info/RECORD
