Metadata-Version: 2.1
Name: kimi-craw
Version: 1.0.5
Summary: kimi_craw
Author: windheart
Author-email: 2916311184@qq.com
Classifier: Programming Language :: Python :: 3
Classifier: License :: OSI Approved :: MIT License
Classifier: Operating System :: OS Independent
Requires-Python: >=3
License-File: LICENSE
Requires-Dist: requests
Requires-Dist: qrcode
